LICENSE
MANIFEST.in
README.rst
helga_cowsay.py
setup.py
helga_cowsay.egg-info/PKG-INFO
helga_cowsay.egg-info/SOURCES.txt
helga_cowsay.egg-info/dependency_links.txt
helga_cowsay.egg-info/entry_points.txt
helga_cowsay.egg-info/top_level.txt
helga_cowsay.egg-info/zip-safe