Metadata-Version: 1.1
Name: helga-cowsay
Version: 1.1.2
Summary: cowsay
Home-page: https://github.com/michaelorr/helga-cowsay
Author: Michael Orr
Author-email: michael@orr.co
License: LICENSE
Keywords: irc bot cow cowsay
Platform: UNKNOWN
Classifier: Development Status :: 4 - Beta
Classifier: License :: OSI Approved :: GNU General Public License v3 (GPLv3)
Classifier: Operating System :: OS Independent
Classifier: Programming Language :: Python
Classifier: Topic :: Software Development :: Libraries :: Python Modules
Classifier: Topic :: Communications :: Chat :: Internet Relay Chat
